<Properties StartupConfiguration="{1DB00857-48CB-44C6-9149-3A420D86861B}|Default">
  <MonoDevelop.Ide.ItemProperties.WeatherApp.Android AndroidDesignerPreferredTheme="Theme.DeviceDefault.NoActionBar.Fullscreen" PreferredExecutionTarget="Android.Android_Accelerated_Oreo" />
  <MonoDevelop.Ide.Workbench ActiveDocument="Weather/WeatherApp.UITests/AppInitializer.cs">
    <Files>
      <File FileName="Weather/WeatherApp/MainPage.xaml.cs" Line="16" Column="10" />
      <File FileName="Weather/WeatherApp/MainPage.xaml" Line="29" Column="37" />
      <File FileName="Weather/WeatherApp/obj/Debug/netstandard2.0/MainPage.xaml.g.cs" Line="1" Column="1" />
      <File FileName="Weather/WeatherApp/WeatherData.cs" Line="1" Column="1" />
      <File FileName="Weather/WeatherApp/RestService.cs" Line="1" Column="1" />
      <File FileName="Weather/WeatherApp/LongToDateTimeConverter.cs" Line="1" Column="1" />
      <File FileName="Weather/WeatherApp.iOS/Main.cs" Line="1" Column="1" />
      <File FileName="Weather/WeatherApp/App.xaml" Line="5" Column="15" />
      <File FileName="Weather/WeatherApp/App.xaml.cs" Line="31" Column="33" />
      <File FileName="Weather/WeatherApp.Android/MainActivity.cs" Line="1" Column="1" />
      <File FileName="Weather/WeatherApp.iOS/AppDelegate.cs" Line="1" Column="1" />
      <File FileName="Weather/WeatherApp.UITests/Tests.cs" Line="33" Column="10" />
      <File FileName="Weather/WeatherApp.UITests/AppInitializer.cs" Line="43" Column="1" />
    </Files>
    <Pads>
      <Pad Id="MonoDevelop.UnitTesting.TestPad">
        <State name="__root__">
          <Node name="WeatherApp" expanded="True">
            <Node name="WeatherApp.UITests" expanded="True">
              <Node name="Test Apps" expanded="True" />
              <Node name="WeatherApp" expanded="True">
                <Node name="Tests(Android)" expanded="True" />
                <Node name="Tests(iOS)" expanded="True">
                  <Node name="AppLaunches" selected="True" />
                </Node>
              </Node>
            </Node>
          </Node>
        </State>
      </Pad>
    </Pads>
  </MonoDevelop.Ide.Workbench>
  <MonoDevelop.Ide.DebuggingService.PinnedWatches />
  <MonoDevelop.Ide.Workspace ActiveConfiguration="Debug" />
  <MonoDevelop.Ide.DebuggingService.Breakpoints>
    <BreakpointStore>
      <Breakpoint enabled="false" file="/Users/mac/Documents/Weather/Weather/WeatherApp/MainPage.xaml" relfile="Weather/WeatherApp/MainPage.xaml" line="49" column="27" />
    </BreakpointStore>
  </MonoDevelop.Ide.DebuggingService.Breakpoints>
  <MultiItemStartupConfigurations />
  <MonoDevelop.Ide.ItemProperties.WeatherApp.iOS PreferredExecutionTarget="MonoDevelop.IPhone.IPhoneSimulatorTarget.912B4724-2561-4CD2-987C-B56E4E22EF62" />
</Properties>